toolit/__init__.py
toolit/auto_loader.py
toolit/cli.py
toolit/config.py
toolit/constants.py
toolit/create_apps_and_register.py
toolit/create_tasks_json.py
toolit/decorators.py
toolit/mcp_server.py
toolit/py.typed
toolit/register_all_tool_and_plugins.py
toolit-0.6.0.dist-info/licenses/LICENSE
toolit-0.6.0.dist-info/METADATA
toolit-0.6.0.dist-info/WHEEL
toolit-0.6.0.dist-info/entry_points.txt
toolit-0.6.0.dist-info/top_level.txt
toolit-0.6.0.dist-info/RECORD
