Metadata-Version: 2.4
Name: toolit
Version: 0.6.0
Summary: MCP Server, Typer CLI and vscode tasks in one, provides an easy way to configure your own DevTools and python scripts in a project.
Author: Martin Møldrup
Project-URL: Homepage, https://github.com/martinmoldrup/toolit
Project-URL: Repository, https://github.com/martinmoldrup/toolit
Project-URL: Issues, https://github.com/martinmoldrup/toolit/issues
Project-URL: Changelog, https://github.com/martinmoldrup/toolit/blob/master/CHANGELOG.md
Keywords: mcp,cli,devtools,typer,vscode,scripts,python,toolkit,tools,development,development tools
Classifier: Framework :: Pytest
Classifier: Development Status :: 4 - Beta
Classifier: Intended Audience :: Developers
Classifier: Topic :: Software Development :: Testing
Classifier: Operating System :: OS Independent
Classifier: Programming Language :: Python
Classifier: Programming Language :: Python :: 3.10
Classifier: Programming Language :: Python :: 3.11
Classifier: Programming Language :: Python :: 3.12
Classifier: Programming Language :: Python :: 3.13
Classifier: Programming Language :: Python :: 3.14
Classifier: Programming Language :: Python :: 3 :: Only
Classifier: Programming Language :: Python :: Implementation :: CPython
Classifier: Programming Language :: Python :: Implementation :: PyPy
Classifier: License :: OSI Approved :: GNU General Public License v3 (GPLv3)
Requires-Python: >=3.10
License-File: LICENSE
Requires-Dist: toml
Requires-Dist: typer
Provides-Extra: mcp
Requires-Dist: mcp[cli]; extra == "mcp"
Dynamic: license-file
